godkjenn/__init__.py
godkjenn/artifact.py
godkjenn/cli.py
godkjenn/commands.py
godkjenn/comparators.py
godkjenn/diff_selector.py
godkjenn/verification.py
godkjenn/integration/__init__.py
godkjenn/integration/pytest_plugin.py
godkjenn/vaults/__init__.py
godkjenn/vaults/fs_vault.py
godkjenn-7.2.1.dist-info/LICENSE
godkjenn-7.2.1.dist-info/METADATA
godkjenn-7.2.1.dist-info/WHEEL
godkjenn-7.2.1.dist-info/entry_points.txt
godkjenn-7.2.1.dist-info/top_level.txt
godkjenn-7.2.1.dist-info/RECORD
